pycw7_ansible/__init__.py
pycw7_ansible/comware.py
pycw7_ansible/errors.py
pycw7_ansible/ansible/library/comware_TelemetryFlowTrace.py
pycw7_ansible/ansible/library/comware_aaa.py
pycw7_ansible/ansible/library/comware_acl.py
pycw7_ansible/ansible/library/comware_bfd.py
pycw7_ansible/ansible/library/comware_bgp_af.py
pycw7_ansible/ansible/library/comware_bgp_global.py
pycw7_ansible/ansible/library/comware_bgp_group.py
pycw7_ansible/ansible/library/comware_clean_erase.py
pycw7_ansible/ansible/library/comware_command.py
pycw7_ansible/ansible/library/comware_compare.py
pycw7_ansible/ansible/library/comware_config.py
pycw7_ansible/ansible/library/comware_dldp.py
pycw7_ansible/ansible/library/comware_evpn.py
pycw7_ansible/ansible/library/comware_facts.py
pycw7_ansible/ansible/library/comware_file_copy.py
pycw7_ansible/ansible/library/comware_ftp.py
pycw7_ansible/ansible/library/comware_hwtacacs.py
pycw7_ansible/ansible/library/comware_iface_stp.py
pycw7_ansible/ansible/library/comware_igmp.py
pycw7_ansible/ansible/library/comware_install_config.py
pycw7_ansible/ansible/library/comware_install_os.py
pycw7_ansible/ansible/library/comware_interface.py
pycw7_ansible/ansible/library/comware_intfState.py
pycw7_ansible/ansible/library/comware_ipinterface.py
pycw7_ansible/ansible/library/comware_irf_members.py
pycw7_ansible/ansible/library/comware_irf_ports.py
pycw7_ansible/ansible/library/comware_isis_global.py
pycw7_ansible/ansible/library/comware_isis_interface.py
pycw7_ansible/ansible/library/comware_l2vpn_global.py
pycw7_ansible/ansible/library/comware_lacp.py
pycw7_ansible/ansible/library/comware_license.py
pycw7_ansible/ansible/library/comware_lldp.py
pycw7_ansible/ansible/library/comware_lldp_global.py
pycw7_ansible/ansible/library/comware_lldp_interface.py
pycw7_ansible/ansible/library/comware_local_user.py
pycw7_ansible/ansible/library/comware_log.py
pycw7_ansible/ansible/library/comware_log_source.py
pycw7_ansible/ansible/library/comware_loghost.py
pycw7_ansible-1.0.0.dist-info/licenses/LICENSE
pycw7_ansible-1.0.0.dist-info/METADATA
pycw7_ansible-1.0.0.dist-info/WHEEL
pycw7_ansible-1.0.0.dist-info/top_level.txt
pycw7_ansible-1.0.0.dist-info/RECORD
