Metadata-Version: 2.4
Name: pycw7-ansible
Version: 1.0.0
Summary: Python package to simplify working with Comware7 Based devices
Author-email: arthurcadore <arthurbarcella.ifsc@gmail.com>
License: (c) Copyright 2016 Hewlett Packard Enterprise Development LP Licensed under the Apache License, Version 2.0
Project-URL: Homepage, https://github.com/arthurcadore/pycw7-ansible
Project-URL: Repository, https://github.com/arthurcadore/pycw7-ansible
Project-URL: Bug Tracker, https://github.com/arthurcadore/pycw7-ansible/issues
Requires-Python: >=3.7
License-File: LICENSE
Requires-Dist: textfsm==1.1.0
Requires-Dist: lxml
Requires-Dist: ncclient
Requires-Dist: scp
Requires-Dist: ipaddr>=2.1.11
Requires-Dist: paramiko
Dynamic: license-file
